GTST/MMD.py
GTST/MONK.py
GTST/__init__.py
GTST/glasso.py
GTST/kernels/DeepKernel.py
GTST/kernels/GNTK.py
GTST/kernels/RandomWalk.py
GTST/kernels/WWL.py
GTST/kernels/__init__.py
GTST-0.0.6.dist-info/LICENSE
GTST-0.0.6.dist-info/METADATA
GTST-0.0.6.dist-info/WHEEL
GTST-0.0.6.dist-info/top_level.txt
GTST-0.0.6.dist-info/RECORD
