Metadata-Version: 2.1
Name: GTST
Version: 0.0.6
Summary: A package for comparing two samples of graphs
Home-page: https://github.com/ragnarlevi/GTST
Author: Ragnar Leví Guðmundarson
Author-email: rlg2000@hw.ac.uk
License: MIT
Project-URL: Bug Tracker, https://github.com/ragnarlevi/GTST/issues
Keywords: graph two sample testing,MMD,graph kernel
Platform: unix
Platform: linux
Platform: osx
Platform: cygwin
Platform: win32
Classifier: Programming Language :: Python :: 3
Classifier: Programming Language :: Python :: 3 :: Only
Classifier: Programming Language :: Python :: 3.7
Classifier: Programming Language :: Python :: 3.8
Classifier: Programming Language :: Python :: 3.9
Classifier: Programming Language :: Python :: 3.10
Classifier: License :: OSI Approved :: MIT License
Classifier: Operating System :: OS Independent
Requires-Python: >=3.7
License-File: LICENSE
Requires-Dist: scipy (>=1.6.1)
Requires-Dist: tqdm (>=4.59.0)
Requires-Dist: numpy (>=1.20.1)
Requires-Dist: networkx (>=2.5)
Requires-Dist: POT (>=0.8.2)
Requires-Dist: scikit-learn (>=1.0.2)
Provides-Extra: testing
Requires-Dist: pytest (>=7.3.0) ; extra == 'testing'
Requires-Dist: pytest-cov (>=2.0) ; extra == 'testing'
Requires-Dist: tox (>=3.24) ; extra == 'testing'
Requires-Dist: grakel (>=0.1.8) ; extra == 'testing'
Requires-Dist: gensim (>=4.2.0) ; extra == 'testing'
